testsolar_testtool_sdk_py2/__init__.py
testsolar_testtool_sdk_py2/decoder.py
testsolar_testtool_sdk_py2/reporter.py
testsolar_testtool_sdk_py2/model/__init__.py
testsolar_testtool_sdk_py2/model/encoder.py
testsolar_testtool_sdk_py2/model/load.py
testsolar_testtool_sdk_py2/model/param.py
testsolar_testtool_sdk_py2/model/testresult.py
testsolar_testtool_sdk_py2-0.4.7.dist-info/METADATA
testsolar_testtool_sdk_py2-0.4.7.dist-info/WHEEL
testsolar_testtool_sdk_py2-0.4.7.dist-info/licenses/LICENSE
testsolar_testtool_sdk_py2-0.4.7.dist-info/RECORD
