Metadata-Version: 2.3
Name: testsolar-testtool-sdk-py2
Version: 0.4.7
Summary: Python2 SDK for TestSolar testtool
Project-URL: repository, https://github.com/OpenTestSolar/testtool-sdk-python-py2
Author-email: asiazhang <asiazhang2002@gmail.com>
License: Apache License 2.0
Keywords: testsolar
Classifier: Development Status :: 4 - Beta
Classifier: Intended Audience :: Developers
Classifier: Programming Language :: Python
Classifier: Programming Language :: Python :: 2
Classifier: Programming Language :: Python :: 2.7
Classifier: Programming Language :: Python :: 3
Requires-Python: >=2.7
Requires-Dist: enum34>=1.1.10
Requires-Dist: simplejson>=3.19.3
Requires-Dist: six>=1.16.0
Requires-Dist: typing>=3.10; python_version < '3.5'
